utilis/__init__.py
utilis/base/__init__.py
utilis/base/context.py
utilis/test/__init__.py
utilis/test/context_test.py
utilis/test/res/simple.tpl
utilis-0.1.3.dist-info/top_level.txt
utilis-0.1.3.dist-info/entry_points.txt
utilis-0.1.3.dist-info/METADATA
utilis-0.1.3.dist-info/DESCRIPTION.rst
utilis-0.1.3.dist-info/metadata.json
utilis-0.1.3.dist-info/WHEEL
utilis-0.1.3.dist-info/RECORD
